LICENSE.txt
README.md
setup.cfg
setup.py
techlearn/__init__.py
techlearn/data_processing.py
techlearn/output_score.py
techlearn.egg-info/PKG-INFO
techlearn.egg-info/SOURCES.txt
techlearn.egg-info/dependency_links.txt
techlearn.egg-info/top_level.txt