Metadata-Version: 2.1
Name: techlearn
Version: 2.0.3
Summary: TestProgram
Home-page: https://github.com/GodOn514/TechLearn
Author: WhereIsTom
Author-email: wzzhangzheyuan@163.com
License: MIT
Platform: UNKNOWN
License-File: LICENSE.txt
